fetchtv_cli/__init__.py
fetchtv_cli/_version.py
fetchtv_cli/fetchtv_cli.py
fetchtv_cli/helpers/__init__.py
fetchtv_cli/helpers/upnp.py
fetchtv_cli-3.0.5.dist-info/METADATA
fetchtv_cli-3.0.5.dist-info/WHEEL
fetchtv_cli-3.0.5.dist-info/entry_points.txt
fetchtv_cli-3.0.5.dist-info/licenses/LICENSE
fetchtv_cli-3.0.5.dist-info/RECORD
