Metadata-Version: 2.4
Name: fetchtv-cli
Version: 3.0.5
Summary: A CLI tool to download recordings from Fetch TV boxes using UPnP.
Project-URL: Documentation, https://github.com/lingfish/fetchtv-cli#readme
Project-URL: Issues, https://github.com/lingfish/fetchtv-cli/issues
Project-URL: Source, https://github.com/lingfish/fetchtv-cli
Author-email: lingfish <jason@lucid.net.au>
License-Expression: MIT
License-File: LICENSE
Classifier: Development Status :: 5 - Production/Stable
Classifier: Programming Language :: Python
Classifier: Programming Language :: Python :: 3.9
Classifier: Programming Language :: Python :: 3.10
Classifier: Programming Language :: Python :: 3.11
Classifier: Programming Language :: Python :: 3.12
Classifier: Programming Language :: Python :: Implementation :: CPython
Classifier: Programming Language :: Python :: Implementation :: PyPy
Requires-Python: >=3.9
Requires-Dist: click
Requires-Dist: jsonpickle>=2.0.0
Requires-Dist: requests>=2.25.1
Requires-Dist: rich
